odoo8_addon_l10n_de_location_nuts-8.0.1.0.0.99.dev6-py2.7-nspkg.pth
odoo8_addon_l10n_de_location_nuts-8.0.1.0.0.99.dev6.dist-info/top_level.txt
odoo8_addon_l10n_de_location_nuts-8.0.1.0.0.99.dev6.dist-info/WHEEL
odoo8_addon_l10n_de_location_nuts-8.0.1.0.0.99.dev6.dist-info/RECORD
odoo8_addon_l10n_de_location_nuts-8.0.1.0.0.99.dev6.dist-info/metadata.json
odoo8_addon_l10n_de_location_nuts-8.0.1.0.0.99.dev6.dist-info/DESCRIPTION.rst
odoo8_addon_l10n_de_location_nuts-8.0.1.0.0.99.dev6.dist-info/METADATA
odoo8_addon_l10n_de_location_nuts-8.0.1.0.0.99.dev6.dist-info/namespace_packages.txt
odoo_addons/l10n_de_location_nuts/__openerp__.py
odoo_addons/l10n_de_location_nuts/hooks.py
odoo_addons/l10n_de_location_nuts/__init__.py
odoo_addons/l10n_de_location_nuts/README.rst
odoo_addons/l10n_de_location_nuts/i18n/es.po
odoo_addons/l10n_de_location_nuts/wizard/nuts_import.py
odoo_addons/l10n_de_location_nuts/wizard/__init__.py
odoo_addons/l10n_de_location_nuts/static/description/icon.png
