Metadata-Version: 2.0
Name: odoo8-addon-l10n-de-location-nuts
Version: 8.0.1.0.0.99.dev6
Summary: NUTS specific options for German
Home-page: http://www.antiun.com
Author: UNKNOWN
Author-email: UNKNOWN
License: AGPL-3
Platform: UNKNOWN
Requires-Dist: odoo (<9.0a,>=8.0a)
Requires-Dist: odoo8-addon-base-location-nuts
Requires-Dist: odoo8-addon-l10n-de-country-states
Classifier: Programming Language :: Python :: 2.7
Classifier: Framework :: Odoo
Classifier: License :: OSI Approved :: GNU Affero General Public License v3
